dagster_salesforce/__init__.py
dagster_salesforce/credentials.py
dagster_salesforce/resource.py
dagster_salesforce/utils.py
dagster_salesforce-0.0.2.dist-info/METADATA
dagster_salesforce-0.0.2.dist-info/WHEEL
dagster_salesforce-0.0.2.dist-info/top_level.txt
dagster_salesforce-0.0.2.dist-info/RECORD
