Metadata-Version: 2.4
Name: dagster-salesforce
Version: 0.0.2
Summary: Dagster integration library for Salesforce
Requires-Python: >=3.10
Requires-Dist: dagster>=1.11.0
Requires-Dist: simple-salesforce>=1.12.9
